envipyarc/__init__.py
envipyarc/gptoolbox.py
envipyarc/esri/projecttemplates/ENVIPyManagement.aptx
envipyarc/esri/projecttemplates/README.md
envipyarc/esri/toolboxes/ENVI Management Tools.ConfigureENVIEnvironment.pyt.xml
envipyarc/esri/toolboxes/ENVI Management Tools.CreateENVIToolbox.pyt.xml
envipyarc/esri/toolboxes/ENVI Management Tools.pyt
envipyarc/esri/toolboxes/ENVI Management Tools.pyt.xml
envipyarc/templates/__init__.py
envipyarc/templates/enviagcrops.py
envipyarc/templates/envicoordsys.py
envipyarc/templates/enviraster.py
envipyarc/templates/envirasterarray.py
envipyarc/templates/envirasterseries.py
envipyarc/templates/envirasterseriesarray.py
envipyarc/templates/enviroi.py
envipyarc/templates/enviroiarray.py
envipyarc/templates/envivector.py
envipyarc/templates/sarscapecoordsysarray.py
envipyarc/templates/sarscapedata.py
envipyarc/templates/sarscapedataarray.py
envipyarc-1.0.11.data/scripts/createenvitoolbox.py
envipyarc-1.0.11.dist-info/DESCRIPTION.rst
envipyarc-1.0.11.dist-info/METADATA
envipyarc-1.0.11.dist-info/RECORD
envipyarc-1.0.11.dist-info/WHEEL
envipyarc-1.0.11.dist-info/metadata.json
envipyarc-1.0.11.dist-info/top_level.txt
