Metadata-Version: 2.0
Name: envipyarc
Version: 1.0.11
Summary: ENVI Python Tools for ArcGIS
Home-page: https://github.com/envi-idl/envipyarc
Author: Harris Geospatial Solutions, Inc.
Author-email: UNKNOWN
License: MIT
Keywords: envi idl
Platform: UNKNOWN
Requires-Dist: envipyengine (>=1.0.5)
Requires-Dist: envipyarclib
